cdk_kaniko/__init__.py
cdk_kaniko/py.typed
cdk_kaniko/_jsii/__init__.py
cdk_kaniko/_jsii/cdk-kaniko@2.0.7.jsii.tgz
cdk_kaniko-2.0.7.dist-info/LICENSE
cdk_kaniko-2.0.7.dist-info/METADATA
cdk_kaniko-2.0.7.dist-info/WHEEL
cdk_kaniko-2.0.7.dist-info/top_level.txt
cdk_kaniko-2.0.7.dist-info/RECORD
